adbb/ISO-639-2_utf-8.txt
adbb/__init__.py
adbb/anames.py
adbb/animeobjs.py
adbb/commands.py
adbb/db.py
adbb/errors.py
adbb/fileinfo.py
adbb/link.py
adbb/mapper.py
adbb/responses.py
adbb-2.dist-info/LICENSE
adbb-2.dist-info/METADATA
adbb-2.dist-info/WHEEL
adbb-2.dist-info/top_level.txt
adbb-2.dist-info/RECORD
