Metadata-Version: 2.1
Name: adbb
Version: 2
Summary: Object Oriented AniDB UDP Client Library
Home-page: https://github.com/winterbird-code/adbb
Author: Winterbird
Author-email: adbb@winterbird.org
License: GPLv3
Platform: any
Requires-Dist: SQLAlchemy
